CHANGES.txt
LICENSE.txt
MANIFEST.in
README
setup.cfg
setup.py
docs/_build/html/.buildinfo
docs/_build/html/.nojekyll
docs/_build/html/genindex.html
docs/_build/html/index.html
docs/_build/html/objects.inv
docs/_build/html/py-modindex.html
docs/_build/html/search.html
docs/_build/html/searchindex.js
docs/_build/html/_modules/index.html
docs/_build/html/_modules/pycfgr/config.html
docs/_build/html/_sources/index.rst.txt
docs/_build/html/_sources/source/modules.rst.txt
docs/_build/html/_sources/source/pycfgr.rst.txt
docs/_build/html/_static/ajax-loader.gif
docs/_build/html/_static/basic.css
docs/_build/html/_static/classic.css
docs/_build/html/_static/comment-bright.png
docs/_build/html/_static/comment-close.png
docs/_build/html/_static/comment.png
docs/_build/html/_static/default.css
docs/_build/html/_static/doctools.js
docs/_build/html/_static/down-pressed.png
docs/_build/html/_static/down.png
docs/_build/html/_static/file.png
docs/_build/html/_static/jquery-3.2.1.js
docs/_build/html/_static/jquery.js
docs/_build/html/_static/minus.png
docs/_build/html/_static/plus.png
docs/_build/html/_static/pygments.css
docs/_build/html/_static/searchtools.js
docs/_build/html/_static/sidebar.js
docs/_build/html/_static/underscore-1.3.1.js
docs/_build/html/_static/underscore.js
docs/_build/html/_static/up-pressed.png
docs/_build/html/_static/up.png
docs/_build/html/_static/websupport.js
docs/_build/html/source/modules.html
docs/_build/html/source/pycfgr.html
pycfgr/__init__.py
pycfgr/config.py
pycfgr/readers.py
pycfgr.egg-info/PKG-INFO
pycfgr.egg-info/SOURCES.txt
pycfgr.egg-info/dependency_links.txt
pycfgr.egg-info/requires.txt
pycfgr.egg-info/top_level.txt