Metadata-Version: 1.1
Name: pycfgr
Version: 0.1.1
Summary: Easy config reader with .yaml and .json out-of-the box support
Home-page: https://github.com/sztal/pycfgr
Author: Szymon Talaga
Author-email: stalaga@protonmail.com
License: MIT
Keywords: pycfgr config cfg conf configuration yaml json
Platform: UNKNOWN
Classifier: Development Status :: 3 - Alpha
Classifier: Intended Audience :: Developers
Classifier: Intended Audience :: System Administrators
Classifier: Intended Audience :: Science/Research
Classifier: Topic :: Software Development
Classifier: Topic :: Software Development :: Libraries :: Python Modules
Classifier: Natural Language :: English
Classifier: Operating System :: OS Independent
Classifier: Programming Language :: Python
Classifier: Programming Language :: Python :: 3.6
Classifier: License :: OSI Approved :: MIT License
